dj_utils/__init__.py
dj_utils/admin.py
dj_utils/apps.py
dj_utils/celery_config.py
dj_utils/handlers.py
dj_utils/models.py
dj_utils/signals.py
dj_utils/tasks.py
dj_utils/tests.py
dj_utils/urls.py
dj_utils/views.py
dj_utils/copy_files/.gitignore
dj_utils/copy_files/Dockerfile
dj_utils/copy_files/__init__.py
dj_utils/copy_files/celery_config.py
dj_utils/copy_files/docker-compose-dev.yml
dj_utils/copy_files/docker-compose.yml
dj_utils/copy_files/entrypoint.sh
dj_utils/copy_files/makemigrations.py
dj_utils/copy_files/requirements.txt
dj_utils/copy_files/settings.py
dj_utils/copy_files/tasks_config.py
dj_utils/copy_files/urls.py
dj_utils/management/__init__.py
dj_utils/management/commands/__init__.py
dj_utils/management/commands/backup.py
dj_utils/management/commands/restore.py
dj_utils/management/commands/utils_env.py
dj_utils/management/commands/utils_init.py
dj_utils/migrations/__init__.py
dj_utils/render/__init__.py
dj_utils/render/api_response_handler.py
dj_utils/render/pagination.py
dj_utils/templates/dj_utils/database_management.html
starco_dj_utils-1.3.0.dist-info/METADATA
starco_dj_utils-1.3.0.dist-info/WHEEL
starco_dj_utils-1.3.0.dist-info/top_level.txt
starco_dj_utils-1.3.0.dist-info/RECORD
