Metadata-Version: 2.4
Name: starco-dj-utils
Version: 1.3.0
Summary: A Django pluggable app for utilities and database management
Author: Mojtaba
Author-email: m.tahmasbi0111@yahoo.com
License: MIT
Classifier: Framework :: Django
Classifier: Programming Language :: Python :: 3
Requires-Dist: Django>=4.0
Requires-Dist: python-telegram-bot==22.5
Requires-Dist: celery
Requires-Dist: redis
Requires-Dist: django-redis
Requires-Dist: django-celery-beat
Requires-Dist: colorama
Requires-Dist: python-dotenv
Requires-Dist: colorlog
Requires-Dist: psycopg2-binary
Requires-Dist: djangorestframework
Requires-Dist: gunicorn
Requires-Dist: uvicorn
Requires-Dist: whitenoise
Requires-Dist: setuptools
Requires-Dist: wheel
Requires-Dist: twine
Requires-Dist: drf-spectacular
Requires-Dist: django-modeltranslation
Requires-Dist: django-cors-headers
Requires-Dist: django-filter
Requires-Dist: pillow
Requires-Dist: starco-utility
Requires-Dist: channels
Dynamic: author
Dynamic: author-email
Dynamic: classifier
Dynamic: license
Dynamic: requires-dist
Dynamic: summary
